spacyjsonnlp/__init__.py
spacyjsonnlp/dependencies.py
spacyjsonnlp/server.py
spacyjsonnlp/spacyjsonnlp.py
tests/__init__.py
tests/mocks.py
tests/test_dependencies.py
tests/test_spacyjsonnlp.py
spacyjsonnlp-0.1.3.dist-info/LICENSE
spacyjsonnlp-0.1.3.dist-info/METADATA
spacyjsonnlp-0.1.3.dist-info/WHEEL
spacyjsonnlp-0.1.3.dist-info/top_level.txt
spacyjsonnlp-0.1.3.dist-info/RECORD
