Metadata-Version: 2.1
Name: spacyjsonnlp
Version: 0.1.3
Summary: The Python spaCy JSON-NLP package
Home-page: https://github.com/dcavar/spaCy-JSON-NLP
Author: Damir Cavar, Oren Baldinger, Maanvitha Gongalla, Anurag Kumar, Murali Kammili
Author-email: damir@cavar.me
License: UNKNOWN
Platform: UNKNOWN
Classifier: Programming Language :: Python :: 3.6
Classifier: Programming Language :: Python :: 3.7
Classifier: License :: OSI Approved :: Apache Software License
Classifier: Operating System :: OS Independent
Requires-Python: >=3.6
Requires-Dist: spacy (>=2.1)
Requires-Dist: neuralcoref (>=4.0)
Requires-Dist: pyjsonnlp (>=0.2.12)
Requires-Dist: benepar[cpu] (>=0.1.2)
Requires-Dist: cython
Requires-Dist: numpy (>=1.14)
